jeli/JELI.py
jeli/JELIImplementation.py
jeli/__init__.py
jeli-1.0.1.dist-info/METADATA
jeli-1.0.1.dist-info/WHEEL
jeli-1.0.1.dist-info/top_level.txt
jeli-1.0.1.dist-info/RECORD
