Metadata-Version: 2.1
Name: jeli
Version: 1.0.1
Summary: Package for Joint Embedding-classifier Learning for Interpretability. Learns feature/item/user embeddings with specific structures, recommends new item-user associations and provides feature importance scores.
Home-page: https://github.com/RECeSS-EU-Project/jeli
Author: Clémence Réda
Author-email: recess-project@proton.me
Classifier: Intended Audience :: Science/Research
Classifier: Topic :: Scientific/Engineering
Classifier: Topic :: Scientific/Engineering :: Artificial Intelligence
Classifier: License :: OSI Approved :: MIT License
Requires-Python: >=3.8
Requires-Dist: numpy
Requires-Dist: pykeen >=1.10.1
Requires-Dist: stanscofi >=2.0.1
Requires-Dist: scikit-learn >=1.2.2
Requires-Dist: scipy >=1.9.3
Requires-Dist: torch-geometric >=2.4.0
Requires-Dist: igraph >=0.11.4
Requires-Dist: torch >=2.1.2
Requires-Dist: tqdm >=4.66.2
Requires-Dist: qnorm >=0.8.1
Requires-Dist: statsmodels >=0.14.1
Requires-Dist: typing-extensions >=4.2.0
